zerocs/__init__.py
zerocs/mate.py
zerocs/zerocs_.py
zerocs/base/__init__.py
zerocs/base/_base.py
zerocs/base/_default_func.py
zerocs/base/_function.py
zerocs/base/base_.py
zerocs/base/default_func_.py
zerocs/base/function_.py
zerocs/fork/__init__.py
zerocs/fork/_func.py
zerocs/fork/fork_.py
zerocs/logger/__init__.py
zerocs/logger/_logger.py
zerocs/logger/logger_.py
zerocs/network/__init__.py
zerocs/network/_network.py
zerocs/network/network_.py
zerocs/rabbitmq/__init__.py
zerocs/rabbitmq/_rabbitmq.py
zerocs/rabbitmq/rabbitmq_.py
zerocs/script/__init__.py
zerocs/script/_queue.py
zerocs/script/queue_.py
zerocs/snowflakeId/__init__.py
zerocs/snowflakeId/_snowflakeId.py
zerocs/snowflakeId/snowflakeId.py
zerocs/sqlite/__init__.py
zerocs/sqlite/_sqlite.py
zerocs/sqlite/sqlite3_.py
zerocs-1.3.dist-info/METADATA
zerocs-1.3.dist-info/WHEEL
zerocs-1.3.dist-info/top_level.txt
zerocs-1.3.dist-info/RECORD
