Metadata-Version: 2.1
Name: zerocs
Version: 1.3
Summary: zerocs
Home-page: https://github.com/ZYPGITA/zerocs
Author: YanPing
Author-email: zyphhxx@foxmail.com
Maintainer: YanPing
Maintainer-email: zyphhxx@foxmail.com
License: MIT License
Classifier: Development Status :: 3 - Alpha
Classifier: Intended Audience :: Developers
Classifier: Topic :: Software Development :: Build Tools
Classifier: License :: OSI Approved :: MIT License
Classifier: Programming Language :: Python :: 3
Requires-Python: >=2.7, !=3.0.*, !=3.1.*, !=3.2.*, !=3.3.*, !=3.4.*
Requires-Dist: nameko
Requires-Dist: pika
